{
  "HVIGOR_OHOS_PLUGIN": {
    "MODULES": [
      {
        "MODULE_NAME": "1043bfc77febe75fafec0c4309faccf1",
        "API_TYPE": "stageMode",
        "INCREMENTAL_TASKS": {
          "COMPILE_ARKTS": true
        }
      }
    ],
    "BUILD_MODE": "debug",
    "USE_NORMALIZED_OHMURL": true
  },
  "HVIGOR": {
    "IS_INCREMENTAL": true,
    "IS_DAEMON": true,
    "IS_PARALLEL": true,
    "IS_HVIGORFILE_TYPE_CHECK": false,
    "TASK_TIME": {
      "1043bfc77febe75fafec0c4309faccf1": {
        "CreateModuleInfo": 644458,
        "ConfigureCmake": 132291,
        "PreCheckSyscap": 161583,
        "ProcessIntegratedHsp": 913167,
        "BuildNativeWithCmake": 391334,
        "SyscapTransform": 1094584,
        "BuildNativeWithNinja": 572333,
        "BuildJS": 1242625,
        "CompileArkTS": 934115084,
        "PackageHap": 415104416,
        "SignHap": 668292,
        "CollectDebugSymbol": 1602958,
        "assembleHap": 112917
      }
    },
    "TOTAL_TIME": 1559380583,
    "BUILD_ID": "202510261702331020"
  }
}